aeom
