Metadata-Version: 2.1
Name: aeom
Version: 0.0.9
Summary: AEOM: Fast and robust clustering in Python
Home-page: https://github.com/nla-group/aeom.git
Author: Xinye Chen, Stefan Güttel
Author-email: xinye.chen@manchester.ac.uk, stefan.guettel@manchester.ac.uk
License: MIT License
Platform: UNKNOWN
Classifier: Intended Audience :: Science/Research
Classifier: Intended Audience :: Developers
Classifier: Programming Language :: Python
Classifier: Topic :: Software Development
Classifier: Topic :: Scientific/Engineering
Classifier: Operating System :: Microsoft :: Windows
Classifier: Operating System :: POSIX
Classifier: Operating System :: Unix
Classifier: Operating System :: MacOS
Classifier: Programming Language :: Python :: 3
License-File: LICENSE
